inirama.py
Inirama-0.8.0.dist-info/DESCRIPTION.rst
Inirama-0.8.0.dist-info/METADATA
Inirama-0.8.0.dist-info/metadata.json
Inirama-0.8.0.dist-info/RECORD
Inirama-0.8.0.dist-info/top_level.txt
Inirama-0.8.0.dist-info/WHEEL
