Metadata-Version: 2.0
Name: Inirama
Version: 0.8.0
Summary: Inirama -- Simplest parser for INI files. Interpolation supported.
